metasub_utils.metadata-0.4.1-py3.6-nspkg.pth
metasub_utils/metadata/__init__.py
metasub_utils/metadata/cli.py
metasub_utils/metadata/constants.py
metasub_utils/metadata/metadata.py
metasub_utils.metadata-0.4.1.dist-info/METADATA
metasub_utils.metadata-0.4.1.dist-info/RECORD
metasub_utils.metadata-0.4.1.dist-info/WHEEL
metasub_utils.metadata-0.4.1.dist-info/entry_points.txt
metasub_utils.metadata-0.4.1.dist-info/namespace_packages.txt
metasub_utils.metadata-0.4.1.dist-info/top_level.txt
